xenfra/__init__.py
xenfra/commands/__init__.py
xenfra/commands/auth.py
xenfra/commands/auth_device.py
xenfra/commands/deployments.py
xenfra/commands/intelligence.py
xenfra/commands/projects.py
xenfra/commands/security_cmd.py
xenfra/main.py
xenfra/utils/__init__.py
xenfra/utils/auth.py
xenfra/utils/codebase.py
xenfra/utils/config.py
xenfra/utils/errors.py
xenfra/utils/file_sync.py
xenfra/utils/security.py
xenfra/utils/validation.py
xenfra-0.4.4.dist-info/WHEEL
xenfra-0.4.4.dist-info/entry_points.txt
xenfra-0.4.4.dist-info/METADATA
xenfra-0.4.4.dist-info/RECORD
