Metadata-Version: 2.3
Name: xenfra
Version: 0.4.4
Summary: Xenfra CLI: Hands for AI to deploy on DigitalOcean.
Author: xenfra-cloud
Author-email: xenfra-cloud <xenfracloud@gmail.com>
Classifier: Programming Language :: Python :: 3
Classifier: License :: OSI Approved :: MIT License
Classifier: Operating System :: OS Independent
Classifier: Development Status :: 3 - Alpha
Classifier: Intended Audience :: Developers
Classifier: Topic :: Software Development :: Build Tools
Classifier: Topic :: System :: Systems Administration
Requires-Dist: click>=8.1.7
Requires-Dist: rich>=14.2.0
Requires-Dist: sqlmodel>=0.0.16
Requires-Dist: python-digitalocean>=1.17.0
Requires-Dist: python-dotenv>=1.2.1
Requires-Dist: pyyaml>=6.0.1
Requires-Dist: fabric>=3.2.2
Requires-Dist: xenfra-sdk>=0.2.2
Requires-Dist: httpx>=0.27.0
Requires-Dist: keyring>=25.7.0
Requires-Dist: keyrings-alt>=5.0.2
Requires-Dist: tenacity>=8.2.3
Requires-Dist: cryptography>=43.0.0
Requires-Dist: toml>=0.10.2
Requires-Dist: pytest>=8.0.0 ; extra == 'test'
Requires-Dist: pytest-mock>=3.12.0 ; extra == 'test'
Requires-Python: >=3.11
Project-URL: Homepage, https://github.com/xenfra-cloud/xenfra-cli
Project-URL: Issues, https://github.com/xenfra-cloud/xenfra-cli/issues
Provides-Extra: test
